{
	"info": {
		"_postman_id": "59704405-1064-4476-a677-20121f7cd1b4",
		"name": "FakeRestAPIG6",
		"schema": "https://schema.getpostman.com/json/collection/v2.1.0/collection.json",
		"_exporter_id": "43573673",
		"_collection_link": "https://g6fakerestapi.postman.co/workspace/FakeRestAPI-Testing~7d4155d6-a96c-4bbe-a0b0-74a8a9f63789/collection/43573673-59704405-1064-4476-a677-20121f7cd1b4?action=share&source=collection_link&creator=43573673"
	},
	"item": [
		{
			"name": "Activities",
			"item": [
				{
					"name": "Get all Activities",
					"request": {
						"method": "GET",
						"header": [],
						"url": {
							"raw": "https://fakerestapi.azurewebsites.net/api/v1/Activities",
							"protocol": "https",
							"host": [
								"fakerestapi",
								"azurewebsites",
								"net"
							],
							"path": [
								"api",
								"v1",
								"Activities"
							]
						}
					},
					"response": []
				},
				{
					"name": "Get Activity",
					"request": {
						"method": "GET",
						"header": [],
						"url": {
							"raw": "https://fakerestapi.azurewebsites.net/api/v1/Activities/3",
							"protocol": "https",
							"host": [
								"fakerestapi",
								"azurewebsites",
								"net"
							],
							"path": [
								"api",
								"v1",
								"Activities",
								"3"
							]
						}
					},
					"response": []
				},
				{
					"name": "Get Activity",
					"request": {
						"method": "GET",
						"header": [],
						"url": {
							"raw": "https://fakerestapi.azurewebsites.net/api/v1/Activities/9999999",
							"protocol": "https",
							"host": [
								"fakerestapi",
								"azurewebsites",
								"net"
							],
							"path": [
								"api",
								"v1",
								"Activities",
								"9999999"
							]
						}
					},
					"response": []
				},
				{
					"name": "Create Activity",
					"request": {
						"method": "POST",
						"header": [],
						"body": {
							"mode": "raw",
							"raw": "{\r\n    \"id\": 41,\r\n    \"title\": \"Activity 41\",\r\n    \"dueDate\": \"2025-07-18T18:20:25.4922958+00:00\",\r\n    \"completed\": false\r\n  }",
							"options": {
								"raw": {
									"language": "json"
								}
							}
						},
						"url": {
							"raw": "https://fakerestapi.azurewebsites.net/api/v1/Activities",
							"protocol": "https",
							"host": [
								"fakerestapi",
								"azurewebsites",
								"net"
							],
							"path": [
								"api",
								"v1",
								"Activities"
							]
						}
					},
					"response": []
				},
				{
					"name": "Create Activity",
					"request": {
						"method": "POST",
						"header": [],
						"body": {
							"mode": "raw",
							"raw": "{\r\n    \r\n}",
							"options": {
								"raw": {
									"language": "json"
								}
							}
						},
						"url": {
							"raw": "https://fakerestapi.azurewebsites.net/api/v1/Activities",
							"protocol": "https",
							"host": [
								"fakerestapi",
								"azurewebsites",
								"net"
							],
							"path": [
								"api",
								"v1",
								"Activities"
							]
						}
					},
					"response": []
				},
				{
					"name": "Create Activity",
					"request": {
						"method": "POST",
						"header": [],
						"body": {
							"mode": "raw",
							"raw": "{\r\n    \"id\": 3,\r\n    \"title\": \"Activity 41\",\r\n    \"dueDate\": \"2025-07-18T18:20:25.4922958+00:00\",\r\n    \"completed\": false\r\n  }",
							"options": {
								"raw": {
									"language": "json"
								}
							}
						},
						"url": {
							"raw": "https://fakerestapi.azurewebsites.net/api/v1/Activities",
							"protocol": "https",
							"host": [
								"fakerestapi",
								"azurewebsites",
								"net"
							],
							"path": [
								"api",
								"v1",
								"Activities"
							]
						}
					},
					"response": []
				},
				{
					"name": "Update Activity",
					"request": {
						"method": "PUT",
						"header": [],
						"body": {
							"mode": "raw",
							"raw": "{\r\n    \"title\": \"Test API Actualizada\",\r\n    \"dueDate\":  \"2025-07-19T08:25:38.335Z\",\r\n    \"completed\": true\r\n}",
							"options": {
								"raw": {
									"language": "json"
								}
							}
						},
						"url": {
							"raw": "https://fakerestapi.azurewebsites.net/api/v1/Activities/3",
							"protocol": "https",
							"host": [
								"fakerestapi",
								"azurewebsites",
								"net"
							],
							"path": [
								"api",
								"v1",
								"Activities",
								"3"
							]
						}
					},
					"response": []
				},
				{
					"name": "Update Activity",
					"request": {
						"method": "PUT",
						"header": [],
						"body": {
							"mode": "raw",
							"raw": "{\r\n    \"title\": \"Test API Actualizada\",\r\n    \"dueDate\":  \"2025-07-19T08:25:38.335Z\",\r\n    \"completed\": true\r\n}",
							"options": {
								"raw": {
									"language": "json"
								}
							}
						},
						"url": {
							"raw": "https://fakerestapi.azurewebsites.net/api/v1/Activities/999666",
							"protocol": "https",
							"host": [
								"fakerestapi",
								"azurewebsites",
								"net"
							],
							"path": [
								"api",
								"v1",
								"Activities",
								"999666"
							]
						}
					},
					"response": []
				},
				{
					"name": "Delete Activity",
					"request": {
						"method": "DELETE",
						"header": [],
						"body": {
							"mode": "raw",
							"raw": "{\r\n    \"title\": \"Test API Actualizada\",\r\n    \"dueDate\":  \"2025-07-19T08:25:38.335Z\",\r\n    \"completed\": true\r\n}",
							"options": {
								"raw": {
									"language": "json"
								}
							}
						},
						"url": {
							"raw": "https://fakerestapi.azurewebsites.net/api/v1/Activities/3",
							"protocol": "https",
							"host": [
								"fakerestapi",
								"azurewebsites",
								"net"
							],
							"path": [
								"api",
								"v1",
								"Activities",
								"3"
							]
						}
					},
					"response": []
				},
				{
					"name": "Delete Activity",
					"request": {
						"method": "DELETE",
						"header": [],
						"body": {
							"mode": "raw",
							"raw": "{\r\n    \"title\": \"Test API Actualizada\",\r\n    \"dueDate\":  \"2025-07-19T08:25:38.335Z\",\r\n    \"completed\": true\r\n}",
							"options": {
								"raw": {
									"language": "json"
								}
							}
						},
						"url": {
							"raw": "https://fakerestapi.azurewebsites.net/api/v1/Activities/333666",
							"protocol": "https",
							"host": [
								"fakerestapi",
								"azurewebsites",
								"net"
							],
							"path": [
								"api",
								"v1",
								"Activities",
								"333666"
							]
						}
					},
					"response": []
				}
			],
			"description": "Endpoints Activities"
		},
		{
			"name": "Authors",
			"item": [
				{
					"name": "Read all Authors",
					"request": {
						"method": "GET",
						"header": [],
						"url": {
							"raw": "{{base_url}}{{authors}}",
							"host": [
								"{{base_url}}{{authors}}"
							]
						}
					},
					"response": []
				},
				{
					"name": "Read Author with non-existent ID",
					"request": {
						"method": "GET",
						"header": [],
						"url": {
							"raw": "{{base_url}}{{authors}}/1000",
							"host": [
								"{{base_url}}{{authors}}"
							],
							"path": [
								"1000"
							]
						}
					},
					"response": []
				},
				{
					"name": "Read Author with invalid ID",
					"request": {
						"method": "GET",
						"header": [],
						"url": {
							"raw": "{{base_url}}{{authors}}/abc",
							"host": [
								"{{base_url}}{{authors}}"
							],
							"path": [
								"abc"
							]
						}
					},
					"response": []
				},
				{
					"name": "Method not Allowed",
					"request": {
						"method": "PUT",
						"header": [],
						"url": {
							"raw": "{{base_url}}{{authors}}",
							"host": [
								"{{base_url}}{{authors}}"
							]
						}
					},
					"response": []
				},
				{
					"name": "Read one Author By ID",
					"request": {
						"method": "GET",
						"header": [],
						"url": {
							"raw": "{{base_url}}{{authors}}/1",
							"host": [
								"{{base_url}}{{authors}}"
							],
							"path": [
								"1"
							]
						}
					},
					"response": []
				},
				{
					"name": "Read Authors By ID Book",
					"request": {
						"method": "GET",
						"header": [],
						"url": {
							"raw": "{{base_url}}{{authors}}/authors/books/1000",
							"host": [
								"{{base_url}}{{authors}}"
							],
							"path": [
								"authors",
								"books",
								"1000"
							]
						}
					},
					"response": []
				},
				{
					"name": "Read Author with non-existent ID",
					"request": {
						"method": "GET",
						"header": [],
						"url": {
							"raw": "{{base_url}}{{authors}}/authors/books/1000",
							"host": [
								"{{base_url}}{{authors}}"
							],
							"path": [
								"authors",
								"books",
								"1000"
							]
						}
					},
					"response": []
				},
				{
					"name": "Create Authors",
					"request": {
						"method": "POST",
						"header": [],
						"body": {
							"mode": "raw",
							"raw": "{\r\n    \"id\": 3000,\r\n    \"idBook\": 1,\r\n    \"firstName\": \"Juan\",\r\n    \"lastName\": \"Gonzales\"\r\n}",
							"options": {
								"raw": {
									"language": "json"
								}
							}
						},
						"url": {
							"raw": "{{base_url}}{{authors}}",
							"host": [
								"{{base_url}}{{authors}}"
							]
						}
					},
					"response": []
				},
				{
					"name": "Create Author with invalid data",
					"request": {
						"method": "POST",
						"header": [],
						"body": {
							"mode": "raw",
							"raw": "{\r\n    \"id\": 3001\r\n}",
							"options": {
								"raw": {
									"language": "json"
								}
							}
						},
						"url": {
							"raw": "{{base_url}}{{authors}}",
							"host": [
								"{{base_url}}{{authors}}"
							]
						}
					},
					"response": []
				},
				{
					"name": "Create Author with invalid idBook",
					"request": {
						"method": "POST",
						"header": [],
						"body": {
							"mode": "raw",
							"raw": "{\r\n    \"id\": 3002,\r\n    \"idBook\": 999999,\r\n    \"firstName\": \"Luis\",\r\n    \"lastName\": \"Torres\"\r\n}",
							"options": {
								"raw": {
									"language": "json"
								}
							}
						},
						"url": {
							"raw": "{{base_url}}{{authors}}",
							"host": [
								"{{base_url}}{{authors}}"
							]
						}
					},
					"response": []
				},
				{
					"name": "Create Author with empty data",
					"request": {
						"method": "POST",
						"header": [],
						"body": {
							"mode": "raw",
							"raw": "{\r\n   \r\n}",
							"options": {
								"raw": {
									"language": "json"
								}
							}
						},
						"url": {
							"raw": "{{base_url}}{{authors}}",
							"host": [
								"{{base_url}}{{authors}}"
							]
						}
					},
					"response": []
				},
				{
					"name": "Create Author with duplicate ID",
					"request": {
						"method": "POST",
						"header": [],
						"body": {
							"mode": "raw",
							"raw": "{\r\n    \"id\": 1,\r\n    \"idBook\": 1,\r\n    \"firstName\": \"Juan\",\r\n    \"lastName\": \"Gonzales\"\r\n}",
							"options": {
								"raw": {
									"language": "json"
								}
							}
						},
						"url": {
							"raw": "{{base_url}}{{authors}}",
							"host": [
								"{{base_url}}{{authors}}"
							]
						}
					},
					"response": []
				},
				{
					"name": "Update an Author By ID",
					"request": {
						"method": "PUT",
						"header": [],
						"body": {
							"mode": "raw",
							"raw": "{\r\n    \"id\": 1,\r\n    \"idBook\": 1,\r\n    \"firstName\": \"Juan Carlos\",\r\n    \"lastName\": \"Ramírez\"\r\n}",
							"options": {
								"raw": {
									"language": "json"
								}
							}
						},
						"url": {
							"raw": "{{base_url}}{{authors}}/1",
							"host": [
								"{{base_url}}{{authors}}"
							],
							"path": [
								"1"
							]
						}
					},
					"response": []
				},
				{
					"name": "Update non-existent Author",
					"request": {
						"method": "PUT",
						"header": [],
						"body": {
							"mode": "raw",
							"raw": "{\r\n    \"id\": 9999,\r\n    \"idBook\": 1,\r\n    \"firstName\": \"Pedro\",\r\n    \"lastName\": \"Mendoza\"\r\n}",
							"options": {
								"raw": {
									"language": "json"
								}
							}
						},
						"url": {
							"raw": "{{base_url}}{{authors}}/9999",
							"host": [
								"{{base_url}}{{authors}}"
							],
							"path": [
								"9999"
							]
						}
					},
					"response": []
				},
				{
					"name": "Update  Author with empty data",
					"request": {
						"method": "PUT",
						"header": [],
						"body": {
							"mode": "raw",
							"raw": "{\r\n    \r\n}",
							"options": {
								"raw": {
									"language": "json"
								}
							}
						},
						"url": {
							"raw": "{{base_url}}{{authors}}/3001",
							"host": [
								"{{base_url}}{{authors}}"
							],
							"path": [
								"3001"
							]
						}
					},
					"response": []
				},
				{
					"name": "Update author with inconsistency between path ID and body",
					"request": {
						"method": "PUT",
						"header": [],
						"body": {
							"mode": "raw",
							"raw": "{\r\n    \"id\": 999,\r\n    \"idBook\": 1,\r\n    \"firstName\": \"Maria\",\r\n    \"lastName\": \"Gomez\"\r\n}",
							"options": {
								"raw": {
									"language": "json"
								}
							}
						},
						"url": {
							"raw": "{{base_url}}{{authors}}/3001",
							"host": [
								"{{base_url}}{{authors}}"
							],
							"path": [
								"3001"
							]
						}
					},
					"response": []
				},
				{
					"name": "Delete an Author By ID",
					"request": {
						"method": "DELETE",
						"header": [],
						"body": {
							"mode": "raw",
							"raw": "{\r\n    \"id\": 0,\r\n    \"idBook\": 1,\r\n    \"firstName\": \"First Name 0\",\r\n    \"lastName\": \"Last Name 0\"\r\n}",
							"options": {
								"raw": {
									"language": "json"
								}
							}
						},
						"url": {
							"raw": "{{base_url}}{{authors}}/3000",
							"host": [
								"{{base_url}}{{authors}}"
							],
							"path": [
								"3000"
							]
						}
					},
					"response": []
				},
				{
					"name": "Delete non-existent Author",
					"request": {
						"method": "DELETE",
						"header": [],
						"body": {
							"mode": "raw",
							"raw": "{\r\n    \"id\": 0,\r\n    \"idBook\": 1,\r\n    \"firstName\": \"First Name 0\",\r\n    \"lastName\": \"Last Name 0\"\r\n}",
							"options": {
								"raw": {
									"language": "json"
								}
							}
						},
						"url": {
							"raw": "{{base_url}}{{authors}}/9999",
							"host": [
								"{{base_url}}{{authors}}"
							],
							"path": [
								"9999"
							]
						}
					},
					"response": []
				},
				{
					"name": "Delete author with invalid ID",
					"request": {
						"method": "DELETE",
						"header": [],
						"body": {
							"mode": "raw",
							"raw": "{\r\n    \"id\": 0,\r\n    \"idBook\": 1,\r\n    \"firstName\": \"First Name 0\",\r\n    \"lastName\": \"Last Name 0\"\r\n}",
							"options": {
								"raw": {
									"language": "json"
								}
							}
						},
						"url": {
							"raw": "{{base_url}}{{authors}}/abc",
							"host": [
								"{{base_url}}{{authors}}"
							],
							"path": [
								"abc"
							]
						}
					},
					"response": []
				},
				{
					"name": "Delete author without ID",
					"request": {
						"method": "DELETE",
						"header": [],
						"body": {
							"mode": "raw",
							"raw": "{\r\n    \"id\": 0,\r\n    \"idBook\": 1,\r\n    \"firstName\": \"First Name 0\",\r\n    \"lastName\": \"Last Name 0\"\r\n}",
							"options": {
								"raw": {
									"language": "json"
								}
							}
						},
						"url": {
							"raw": "{{base_url}}{{authors}}/",
							"host": [
								"{{base_url}}{{authors}}"
							],
							"path": [
								""
							]
						}
					},
					"response": []
				}
			]
		},
		{
			"name": "Books",
			"item": [
				{
					"name": "Read all Books",
					"request": {
						"method": "GET",
						"header": [],
						"url": {
							"raw": "{{base_url}}{{books}}",
							"host": [
								"{{base_url}}{{books}}"
							]
						}
					},
					"response": []
				},
				{
					"name": "Read Book wid invalid ID",
					"request": {
						"method": "GET",
						"header": [],
						"url": {
							"raw": "{{base_url}}{{books}}/abc",
							"host": [
								"{{base_url}}{{books}}"
							],
							"path": [
								"abc"
							]
						}
					},
					"response": []
				},
				{
					"name": "Read a Book By ID",
					"request": {
						"method": "GET",
						"header": [],
						"url": {
							"raw": "{{base_url}}{{books}}/1",
							"host": [
								"{{base_url}}{{books}}"
							],
							"path": [
								"1"
							]
						}
					},
					"response": []
				},
				{
					"name": "Read Book with non-exists ID",
					"request": {
						"method": "GET",
						"header": [],
						"url": {
							"raw": "{{base_url}}{{books}}/500",
							"host": [
								"{{base_url}}{{books}}"
							],
							"path": [
								"500"
							]
						}
					},
					"response": []
				},
				{
					"name": "Create Books",
					"request": {
						"method": "POST",
						"header": [],
						"body": {
							"mode": "raw",
							"raw": "{\r\n    \"id\": 2000,\r\n    \"title\": \"API Testing Book\",\r\n    \"description\": \"Libro de pruebas\",\r\n    \"pageCount\": 100,\r\n    \"excerpt\": \"Este es un libro de prueba\",\r\n    \"publishDate\": \"2025-07-20T00:17:42.685Z\"\r\n}",
							"options": {
								"raw": {
									"language": "json"
								}
							}
						},
						"url": {
							"raw": "{{base_url}}{{books}}",
							"host": [
								"{{base_url}}{{books}}"
							]
						}
					},
					"response": []
				},
				{
					"name": "Create Book with incompleted data",
					"request": {
						"method": "POST",
						"header": [],
						"body": {
							"mode": "raw",
							"raw": "{\r\n    \"id\": 500\r\n}",
							"options": {
								"raw": {
									"language": "json"
								}
							}
						},
						"url": {
							"raw": "{{base_url}}{{books}}",
							"host": [
								"{{base_url}}{{books}}"
							]
						}
					},
					"response": []
				},
				{
					"name": "Create Book with empty values",
					"request": {
						"method": "POST",
						"header": [],
						"body": {
							"mode": "raw",
							"raw": "{\r\n    \r\n}",
							"options": {
								"raw": {
									"language": "json"
								}
							}
						},
						"url": {
							"raw": "{{base_url}}{{books}}",
							"host": [
								"{{base_url}}{{books}}"
							]
						}
					},
					"response": []
				},
				{
					"name": "Create Book with duplicate ID",
					"request": {
						"method": "POST",
						"header": [],
						"body": {
							"mode": "raw",
							"raw": "{\r\n    \"id\": 1,\r\n    \"title\": \"Duplicado\",\r\n    \"description\": \"Prueba duplicado\",\r\n    \"pageCount\": 100,\r\n    \"excerpt\": \"Texto\",\r\n    \"publishDate\": \"2025-07-17T00:00:00\"\r\n}",
							"options": {
								"raw": {
									"language": "json"
								}
							}
						},
						"url": {
							"raw": "{{base_url}}{{books}}",
							"host": [
								"{{base_url}}{{books}}"
							]
						}
					},
					"response": []
				},
				{
					"name": "Update a Book By ID",
					"request": {
						"method": "PUT",
						"header": [],
						"body": {
							"mode": "raw",
							"raw": "{\r\n    \"id\": 1,\r\n    \"title\": \"La sombra del viento\",\r\n    \"description\": \"Novela histórica y de misterio\",\r\n    \"pageCount\": 320,\r\n    \"excerpt\": \"Barcelona, 1945. En un amanecer gris...\",\r\n    \"publishDate\": \"2025-07-17T10:00:00Z\"\r\n}",
							"options": {
								"raw": {
									"language": "json"
								}
							}
						},
						"url": {
							"raw": "{{base_url}}{{books}}/1",
							"host": [
								"{{base_url}}{{books}}"
							],
							"path": [
								"1"
							]
						}
					},
					"response": []
				},
				{
					"name": "Update non-exists Book",
					"request": {
						"method": "PUT",
						"header": [],
						"body": {
							"mode": "raw",
							"raw": "{\r\n    \"id\": 9999,\r\n    \"title\": \"Libro fantasma\",\r\n    \"description\": \"Este libro no debería existir\",\r\n    \"pageCount\": 100,\r\n    \"excerpt\": \"Texto irrelevante\",\r\n    \"publishDate\": \"2025-07-17T10:00:00Z\"\r\n}",
							"options": {
								"raw": {
									"language": "json"
								}
							}
						},
						"url": {
							"raw": "{{base_url}}{{books}}/9999",
							"host": [
								"{{base_url}}{{books}}"
							],
							"path": [
								"9999"
							]
						}
					},
					"response": []
				},
				{
					"name": "Update empty book",
					"request": {
						"method": "PUT",
						"header": [],
						"body": {
							"mode": "raw",
							"raw": "{\r\n    \r\n}",
							"options": {
								"raw": {
									"language": "json"
								}
							}
						},
						"url": {
							"raw": "{{base_url}}{{books}}/3001",
							"host": [
								"{{base_url}}{{books}}"
							],
							"path": [
								"3001"
							]
						}
					},
					"response": []
				},
				{
					"name": "Update error book in the URL",
					"request": {
						"method": "PUT",
						"header": [],
						"body": {
							"mode": "raw",
							"raw": "{\r\n    \"id\": 999,\r\n    \"title\": \"Nuevo título\",\r\n    \"description\": \"Descripción actualizada\",\r\n    \"pageCount\": 150,\r\n    \"excerpt\": \"Texto de prueba\",\r\n    \"publishDate\": \"2025-07-17T12:00:00Z\"\r\n}",
							"options": {
								"raw": {
									"language": "json"
								}
							}
						},
						"url": {
							"raw": "{{base_url}}{{books}}/3001",
							"host": [
								"{{base_url}}{{books}}"
							],
							"path": [
								"3001"
							]
						}
					},
					"response": []
				},
				{
					"name": "Delete a Book By ID",
					"request": {
						"method": "DELETE",
						"header": [],
						"body": {
							"mode": "raw",
							"raw": "{\r\n  \"id\": 0,\r\n  \"title\": \"string\",\r\n  \"description\": \"string\",\r\n  \"pageCount\": 0,\r\n  \"excerpt\": \"string\",\r\n  \"publishDate\": \"2025-07-14T21:08:57.655Z\"\r\n}",
							"options": {
								"raw": {
									"language": "json"
								}
							}
						},
						"url": {
							"raw": "{{base_url}}{{books}}/2000",
							"host": [
								"{{base_url}}{{books}}"
							],
							"path": [
								"2000"
							]
						}
					},
					"response": []
				},
				{
					"name": "Delete non-exists Book",
					"request": {
						"method": "DELETE",
						"header": [],
						"body": {
							"mode": "raw",
							"raw": "{\r\n  \"id\": 0,\r\n  \"title\": \"string\",\r\n  \"description\": \"string\",\r\n  \"pageCount\": 0,\r\n  \"excerpt\": \"string\",\r\n  \"publishDate\": \"2025-07-14T21:08:57.655Z\"\r\n}",
							"options": {
								"raw": {
									"language": "json"
								}
							}
						},
						"url": {
							"raw": "{{base_url}}{{books}}/9999",
							"host": [
								"{{base_url}}{{books}}"
							],
							"path": [
								"9999"
							]
						}
					},
					"response": []
				},
				{
					"name": "Delete book with invalid ID",
					"request": {
						"method": "DELETE",
						"header": [],
						"url": {
							"raw": "{{base_url}}{{books}}/abc",
							"host": [
								"{{base_url}}{{books}}"
							],
							"path": [
								"abc"
							]
						}
					},
					"response": []
				},
				{
					"name": "Delete book without ID",
					"request": {
						"method": "DELETE",
						"header": [],
						"url": {
							"raw": "{{base_url}}{{books}}/",
							"host": [
								"{{base_url}}{{books}}"
							],
							"path": [
								""
							]
						}
					},
					"response": []
				}
			]
		},
		{
			"name": "CoverPhotos",
			"item": [
				{
					"name": "GET - Obtener todas las cover photos",
					"request": {
						"method": "GET",
						"header": [],
						"url": {
							"raw": "https://fakerestapi.azurewebsites.net/api/v1/CoverPhotos",
							"protocol": "https",
							"host": [
								"fakerestapi",
								"azurewebsites",
								"net"
							],
							"path": [
								"api",
								"v1",
								"CoverPhotos"
							]
						}
					},
					"response": []
				},
				{
					"name": "GET - Obtener cover photo por ID válido",
					"request": {
						"method": "GET",
						"header": [],
						"url": {
							"raw": "https://fakerestapi.azurewebsites.net/api/v1/CoverPhotos/1",
							"protocol": "https",
							"host": [
								"fakerestapi",
								"azurewebsites",
								"net"
							],
							"path": [
								"api",
								"v1",
								"CoverPhotos",
								"1"
							]
						}
					},
					"response": []
				},
				{
					"name": "GET - Obtener cover photo por ID inválido",
					"request": {
						"method": "GET",
						"header": [],
						"url": {
							"raw": "https://fakerestapi.azurewebsites.net/api/v1/CoverPhotos/9999",
							"protocol": "https",
							"host": [
								"fakerestapi",
								"azurewebsites",
								"net"
							],
							"path": [
								"api",
								"v1",
								"CoverPhotos",
								"9999"
							]
						}
					},
					"response": []
				},
				{
					"name": "POST - Crear cover photo válida",
					"request": {
						"method": "POST",
						"header": [
							{
								"key": "Content-Type",
								"value": "application/json"
							}
						],
						"body": {
							"mode": "raw",
							"raw": "{\n  \"id\": 101,\n  \"idBook\": 1,\n  \"url\": \"https://example.com/image.jpg\"\n}"
						},
						"url": {
							"raw": "https://fakerestapi.azurewebsites.net/api/v1/CoverPhotos",
							"protocol": "https",
							"host": [
								"fakerestapi",
								"azurewebsites",
								"net"
							],
							"path": [
								"api",
								"v1",
								"CoverPhotos"
							]
						}
					},
					"response": []
				},
				{
					"name": "POST - Crear cover photo sin campo URL",
					"request": {
						"method": "POST",
						"header": [
							{
								"key": "Content-Type",
								"value": "application/json"
							}
						],
						"body": {
							"mode": "raw",
							"raw": "{\n  \"id\": 102,\n  \"idBook\": 1\n}"
						},
						"url": {
							"raw": "https://fakerestapi.azurewebsites.net/api/v1/CoverPhotos",
							"protocol": "https",
							"host": [
								"fakerestapi",
								"azurewebsites",
								"net"
							],
							"path": [
								"api",
								"v1",
								"CoverPhotos"
							]
						}
					},
					"response": []
				},
				{
					"name": "POST - Crear cover photo con ID duplicado",
					"request": {
						"method": "POST",
						"header": [
							{
								"key": "Content-Type",
								"value": "application/json"
							}
						],
						"body": {
							"mode": "raw",
							"raw": "{\n  \"id\": 1,\n  \"idBook\": 1,\n  \"url\": \"https://example.com/image.jpg\"\n}"
						},
						"url": {
							"raw": "https://fakerestapi.azurewebsites.net/api/v1/CoverPhotos",
							"protocol": "https",
							"host": [
								"fakerestapi",
								"azurewebsites",
								"net"
							],
							"path": [
								"api",
								"v1",
								"CoverPhotos"
							]
						}
					},
					"response": []
				},
				{
					"name": "POST - Crear cover photo con URL mal formada",
					"request": {
						"method": "POST",
						"header": [
							{
								"key": "Content-Type",
								"value": "application/json"
							}
						],
						"body": {
							"mode": "raw",
							"raw": "{\n  \"id\": 103,\n  \"idBook\": 1,\n  \"url\": \"not-a-url\"\n}"
						},
						"url": {
							"raw": "https://fakerestapi.azurewebsites.net/api/v1/CoverPhotos",
							"protocol": "https",
							"host": [
								"fakerestapi",
								"azurewebsites",
								"net"
							],
							"path": [
								"api",
								"v1",
								"CoverPhotos"
							]
						}
					},
					"response": []
				},
				{
					"name": "DELETE - Eliminar cover photo existente",
					"request": {
						"method": "DELETE",
						"header": [],
						"url": {
							"raw": "https://fakerestapi.azurewebsites.net/api/v1/CoverPhotos/1",
							"protocol": "https",
							"host": [
								"fakerestapi",
								"azurewebsites",
								"net"
							],
							"path": [
								"api",
								"v1",
								"CoverPhotos",
								"1"
							]
						}
					},
					"response": []
				},
				{
					"name": "DELETE - Eliminar cover photo inexistente",
					"request": {
						"method": "DELETE",
						"header": [],
						"url": {
							"raw": "https://fakerestapi.azurewebsites.net/api/v1/CoverPhotos/9999",
							"protocol": "https",
							"host": [
								"fakerestapi",
								"azurewebsites",
								"net"
							],
							"path": [
								"api",
								"v1",
								"CoverPhotos",
								"9999"
							]
						}
					},
					"response": []
				},
				{
					"name": "PUT - Actualizar cover photo válida",
					"request": {
						"method": "PUT",
						"header": [
							{
								"key": "Content-Type",
								"value": "application/json"
							}
						],
						"body": {
							"mode": "raw",
							"raw": "{\n  \"id\": 2,\n  \"idBook\": 1,\n  \"url\": \"https://example.com/updated.jpg\"\n}"
						},
						"url": {
							"raw": "https://fakerestapi.azurewebsites.net/api/v1/CoverPhotos/2",
							"protocol": "https",
							"host": [
								"fakerestapi",
								"azurewebsites",
								"net"
							],
							"path": [
								"api",
								"v1",
								"CoverPhotos",
								"2"
							]
						}
					},
					"response": []
				},
				{
					"name": "PUT - Actualizar cover photo con ID inexistente",
					"request": {
						"method": "PUT",
						"header": [
							{
								"key": "Content-Type",
								"value": "application/json"
							}
						],
						"body": {
							"mode": "raw",
							"raw": "{\n  \"id\": 9999,\n  \"idBook\": 1,\n  \"url\": \"https://example.com/doesnotexist.jpg\"\n}"
						},
						"url": {
							"raw": "https://fakerestapi.azurewebsites.net/api/v1/CoverPhotos/9999",
							"protocol": "https",
							"host": [
								"fakerestapi",
								"azurewebsites",
								"net"
							],
							"path": [
								"api",
								"v1",
								"CoverPhotos",
								"9999"
							]
						}
					},
					"response": []
				},
				{
					"name": "PATCH - Método no permitido",
					"request": {
						"method": "PATCH",
						"header": [],
						"url": {
							"raw": "https://fakerestapi.azurewebsites.net/api/v1/CoverPhotos/1",
							"protocol": "https",
							"host": [
								"fakerestapi",
								"azurewebsites",
								"net"
							],
							"path": [
								"api",
								"v1",
								"CoverPhotos",
								"1"
							]
						}
					},
					"response": []
				},
				{
					"name": "POST - Crear cover photo con idBook inexistente",
					"request": {
						"method": "POST",
						"header": [
							{
								"key": "Content-Type",
								"value": "application/json"
							}
						],
						"body": {
							"mode": "raw",
							"raw": "{\n  \"id\": 104,\n  \"idBook\": 9999,\n  \"url\": \"https://example.com/image.jpg\"\n}"
						},
						"url": {
							"raw": "https://fakerestapi.azurewebsites.net/api/v1/CoverPhotos",
							"protocol": "https",
							"host": [
								"fakerestapi",
								"azurewebsites",
								"net"
							],
							"path": [
								"api",
								"v1",
								"CoverPhotos"
							]
						}
					},
					"response": []
				},
				{
					"name": "GET - Verificar tipo de contenido",
					"request": {
						"method": "GET",
						"header": [],
						"url": {
							"raw": "https://fakerestapi.azurewebsites.net/api/v1/CoverPhotos/1",
							"protocol": "https",
							"host": [
								"fakerestapi",
								"azurewebsites",
								"net"
							],
							"path": [
								"api",
								"v1",
								"CoverPhotos",
								"1"
							]
						}
					},
					"response": []
				},
				{
					"name": "GET - Validar esquema de respuesta",
					"request": {
						"method": "GET",
						"header": [],
						"url": {
							"raw": "https://fakerestapi.azurewebsites.net/api/v1/CoverPhotos/2",
							"protocol": "https",
							"host": [
								"fakerestapi",
								"azurewebsites",
								"net"
							],
							"path": [
								"api",
								"v1",
								"CoverPhotos",
								"2"
							]
						}
					},
					"response": []
				},
				{
					"name": "PUT parcial sin todos los campos obligatorios",
					"request": {
						"method": "PUT",
						"header": [
							{
								"key": "Content-Type",
								"value": "application/json"
							}
						],
						"body": {
							"mode": "raw",
							"raw": "{\"url\": \"https://example.com/newcover.jpg\"}"
						},
						"url": {
							"raw": "https://fakerestapi.azurewebsites.net/api/v1/CoverPhotos/3",
							"protocol": "https",
							"host": [
								"fakerestapi",
								"azurewebsites",
								"net"
							],
							"path": [
								"api",
								"v1",
								"CoverPhotos",
								"3"
							]
						}
					},
					"response": []
				},
				{
					"name": "POST con campos extra",
					"request": {
						"method": "POST",
						"header": [
							{
								"key": "Content-Type",
								"value": "application/json"
							}
						],
						"body": {
							"mode": "raw",
							"raw": "{\"id\": 201, \"idBook\": 1, \"url\": \"https://example.com/img.jpg\", \"extraField\": \"xyz\"}"
						},
						"url": {
							"raw": "https://fakerestapi.azurewebsites.net/api/v1/CoverPhotos",
							"protocol": "https",
							"host": [
								"fakerestapi",
								"azurewebsites",
								"net"
							],
							"path": [
								"api",
								"v1",
								"CoverPhotos"
							]
						}
					},
					"response": []
				},
				{
					"name": "PATCH no implementado",
					"request": {
						"method": "PATCH",
						"header": [
							{
								"key": "Content-Type",
								"value": "application/json"
							}
						],
						"body": {
							"mode": "raw",
							"raw": "{\"url\": \"https://example.com/updated.jpg\"}"
						},
						"url": {
							"raw": "https://fakerestapi.azurewebsites.net/api/v1/CoverPhotos/1",
							"protocol": "https",
							"host": [
								"fakerestapi",
								"azurewebsites",
								"net"
							],
							"path": [
								"api",
								"v1",
								"CoverPhotos",
								"1"
							]
						}
					},
					"response": []
				},
				{
					"name": "POST con ID no numérico",
					"request": {
						"method": "POST",
						"header": [
							{
								"key": "Content-Type",
								"value": "application/json"
							}
						],
						"body": {
							"mode": "raw",
							"raw": "{\"id\": \"abc\", \"idBook\": 1, \"url\": \"https://example.com/abc.jpg\"}"
						},
						"url": {
							"raw": "https://fakerestapi.azurewebsites.net/api/v1/CoverPhotos",
							"protocol": "https",
							"host": [
								"fakerestapi",
								"azurewebsites",
								"net"
							],
							"path": [
								"api",
								"v1",
								"CoverPhotos"
							]
						}
					},
					"response": []
				},
				{
					"name": "GET con ID negativo",
					"request": {
						"method": "GET",
						"header": [],
						"url": {
							"raw": "https://fakerestapi.azurewebsites.net/api/v1/CoverPhotos/-1",
							"protocol": "https",
							"host": [
								"fakerestapi",
								"azurewebsites",
								"net"
							],
							"path": [
								"api",
								"v1",
								"CoverPhotos",
								"-1"
							]
						}
					},
					"response": []
				}
			]
		},
		{
			"name": "Users",
			"item": [
				{
					"name": "Get all users",
					"request": {
						"method": "GET",
						"header": [],
						"url": {
							"raw": "https://fakerestapi.azurewebsites.net/api/v1/Users",
							"protocol": "https",
							"host": [
								"fakerestapi",
								"azurewebsites",
								"net"
							],
							"path": [
								"api",
								"v1",
								"Users"
							]
						}
					},
					"response": []
				},
				{
					"name": "Get user with ID=1",
					"request": {
						"method": "GET",
						"header": [],
						"url": {
							"raw": "https://fakerestapi.azurewebsites.net/api/v1/Users/1",
							"protocol": "https",
							"host": [
								"fakerestapi",
								"azurewebsites",
								"net"
							],
							"path": [
								"api",
								"v1",
								"Users",
								"1"
							]
						}
					},
					"response": []
				},
				{
					"name": "Create new user",
					"request": {
						"method": "POST",
						"header": [],
						"body": {
							"mode": "raw",
							"raw": "{\r\n  \"id\": 0,\r\n  \"userName\": \"JhoseTest\",\r\n  \"password\": \"123456\"\r\n}",
							"options": {
								"raw": {
									"language": "json"
								}
							}
						},
						"url": {
							"raw": "https://fakerestapi.azurewebsites.net/api/v1/Users",
							"protocol": "https",
							"host": [
								"fakerestapi",
								"azurewebsites",
								"net"
							],
							"path": [
								"api",
								"v1",
								"Users"
							]
						}
					},
					"response": []
				},
				{
					"name": "Update user ID=1",
					"request": {
						"method": "PUT",
						"header": [],
						"body": {
							"mode": "raw",
							"raw": "{\r\n  \"id\": 1,\r\n  \"userName\": \"UsuarioActualizado\",\r\n  \"password\": \"nuevoPassword\"\r\n}",
							"options": {
								"raw": {
									"language": "json"
								}
							}
						},
						"url": {
							"raw": "https://fakerestapi.azurewebsites.net/api/v1/Users/1",
							"protocol": "https",
							"host": [
								"fakerestapi",
								"azurewebsites",
								"net"
							],
							"path": [
								"api",
								"v1",
								"Users",
								"1"
							]
						}
					},
					"response": []
				},
				{
					"name": "Delete user ID=1",
					"request": {
						"method": "DELETE",
						"header": [],
						"body": {
							"mode": "raw",
							"raw": "",
							"options": {
								"raw": {
									"language": "json"
								}
							}
						},
						"url": {
							"raw": "https://fakerestapi.azurewebsites.net/api/v1/Users/1",
							"protocol": "https",
							"host": [
								"fakerestapi",
								"azurewebsites",
								"net"
							],
							"path": [
								"api",
								"v1",
								"Users",
								"1"
							]
						}
					},
					"response": []
				},
				{
					"name": "POST without \"userName\" field",
					"request": {
						"method": "POST",
						"header": [],
						"body": {
							"mode": "raw",
							"raw": "{\"password\":\"123\"}",
							"options": {
								"raw": {
									"language": "json"
								}
							}
						},
						"url": {
							"raw": "https://fakerestapi.azurewebsites.net/api/v1/Users",
							"protocol": "https",
							"host": [
								"fakerestapi",
								"azurewebsites",
								"net"
							],
							"path": [
								"api",
								"v1",
								"Users"
							]
						}
					},
					"response": []
				},
				{
					"name": "DELETE without ID",
					"request": {
						"method": "DELETE",
						"header": [],
						"url": {
							"raw": "https://fakerestapi.azurewebsites.net/api/v1/Users/9999",
							"protocol": "https",
							"host": [
								"fakerestapi",
								"azurewebsites",
								"net"
							],
							"path": [
								"api",
								"v1",
								"Users",
								"9999"
							]
						}
					},
					"response": []
				}
			]
		}
	],
	"event": [
		{
			"listen": "prerequest",
			"script": {
				"type": "text/javascript",
				"packages": {},
				"exec": [
					""
				]
			}
		},
		{
			"listen": "test",
			"script": {
				"type": "text/javascript",
				"packages": {},
				"exec": [
					""
				]
			}
		}
	],
	"variable": [
		{
			"key": "authors",
			"value": "Authors",
			"type": "string"
		},
		{
			"key": "books",
			"value": "Books",
			"type": "string"
		}
	]
}